{
  "type": "Feature",
  "stac_version": "1.0.0",
  "id": "111TRS-R-0106-0007",
  "collection": "ncap-aerial",
  "geometry": {
    "type": "Polygon",
    "coordinates": [
      [
        [
          1.888412,
          47.90282
        ],
        [
          1.913667,
          47.894283
        ],
        [
          1.89466,
          47.879533
        ],
        [
          1.882032,
          47.883803
        ],
        [
          1.888412,
          47.90282
        ]
      ]
    ]
  },
  "bbox": [
    1.882032,
    47.879533,
    1.913667,
    47.90282
  ],
  "properties": {
    "datetime": "1946-01-03T00:00:00Z",
    "naph:tier": "Baseline",
    "naph:sortie": "111TRS/R/0106",
    "naph:perspective": "oblique",
    "naph:camera": "O",
    "naph:identifier": "https://w3id.org/naph/photo/111TRS-R-0106-0007",
    "naph:source": "https://airphotofinder.ncap.org/image/75961",
    "title": "111TRS/R/0106 frame 0007",
    "license": "other"
  },
  "links": [
    {
      "rel": "root",
      "href": "../../catalog.json",
      "type": "application/json"
    },
    {
      "rel": "parent",
      "href": "../../catalog.json",
      "type": "application/json"
    },
    {
      "rel": "self",
      "href": "./111TRS-R-0106-0007.json",
      "type": "application/geo+json"
    },
    {
      "rel": "collection",
      "href": "../../catalog.json",
      "type": "application/json"
    }
  ],
  "assets": {
    "catalogue": {
      "href": "https://airphotofinder.ncap.org/image/75961",
      "title": "Air Photo Finder catalogue record",
      "type": "text/html",
      "roles": [
        "overview",
        "metadata"
      ]
    },
    "image": {
      "href": "https://airphotofinder.ncap.org/image/75961",
      "title": "Digital surrogate (NCAP access copy)",
      "type": "image/tiff",
      "roles": [
        "data"
      ]
    }
  }
}