{
  "type": "Feature",
  "stac_version": "1.0.0",
  "id": "16-LW-0001-0053",
  "collection": "ncap-aerial",
  "geometry": {
    "type": "Polygon",
    "coordinates": [
      [
        [
          -62.933623,
          18.298099
        ],
        [
          -62.91263,
          18.270731
        ],
        [
          -62.941279,
          18.250916
        ],
        [
          -62.962272,
          18.278287
        ],
        [
          -62.933623,
          18.298099
        ]
      ]
    ]
  },
  "bbox": [
    -62.962272,
    18.250916,
    -62.91263,
    18.298099
  ],
  "properties": {
    "datetime": "1956-01-01T00:00:00Z",
    "naph:tier": "Baseline",
    "naph:sortie": "16/LW/0001",
    "naph:perspective": "vertical",
    "naph:camera": "V",
    "naph:identifier": "https://w3id.org/naph/photo/16-LW-0001-0053",
    "naph:source": "https://airphotofinder.ncap.org/image/753259",
    "title": "16/LW/0001 frame 0053",
    "license": "other"
  },
  "links": [
    {
      "rel": "root",
      "href": "../../catalog.json",
      "type": "application/json"
    },
    {
      "rel": "parent",
      "href": "../../catalog.json",
      "type": "application/json"
    },
    {
      "rel": "self",
      "href": "./16-LW-0001-0053.json",
      "type": "application/geo+json"
    },
    {
      "rel": "collection",
      "href": "../../catalog.json",
      "type": "application/json"
    }
  ],
  "assets": {
    "catalogue": {
      "href": "https://airphotofinder.ncap.org/image/753259",
      "title": "Air Photo Finder catalogue record",
      "type": "text/html",
      "roles": [
        "overview",
        "metadata"
      ]
    },
    "image": {
      "href": "https://airphotofinder.ncap.org/image/753259",
      "title": "Digital surrogate (NCAP access copy)",
      "type": "image/tiff",
      "roles": [
        "data"
      ]
    }
  }
}