{
  "type": "Feature",
  "stac_version": "1.0.0",
  "id": "16-LW-0001-0003",
  "collection": "ncap-aerial",
  "geometry": {
    "type": "Polygon",
    "coordinates": [
      [
        [
          -62.987478,
          18.263112
        ],
        [
          -62.959716,
          18.281878
        ],
        [
          -62.940073,
          18.255672
        ],
        [
          -62.967837,
          18.236906
        ],
        [
          -62.987478,
          18.263112
        ]
      ]
    ]
  },
  "bbox": [
    -62.987478,
    18.236906,
    -62.940073,
    18.281878
  ],
  "properties": {
    "datetime": "1956-01-01T00:00:00Z",
    "naph:tier": "Baseline",
    "naph:sortie": "16/LW/0001",
    "naph:perspective": "vertical",
    "naph:camera": "V",
    "naph:identifier": "https://w3id.org/naph/photo/16-LW-0001-0003",
    "naph:source": "https://airphotofinder.ncap.org/image/753158",
    "title": "16/LW/0001 frame 0003",
    "license": "other"
  },
  "links": [
    {
      "rel": "root",
      "href": "../../catalog.json",
      "type": "application/json"
    },
    {
      "rel": "parent",
      "href": "../../catalog.json",
      "type": "application/json"
    },
    {
      "rel": "self",
      "href": "./16-LW-0001-0003.json",
      "type": "application/geo+json"
    },
    {
      "rel": "collection",
      "href": "../../catalog.json",
      "type": "application/json"
    }
  ],
  "assets": {
    "catalogue": {
      "href": "https://airphotofinder.ncap.org/image/753158",
      "title": "Air Photo Finder catalogue record",
      "type": "text/html",
      "roles": [
        "overview",
        "metadata"
      ]
    },
    "image": {
      "href": "https://airphotofinder.ncap.org/image/753158",
      "title": "Digital surrogate (NCAP access copy)",
      "type": "image/tiff",
      "roles": [
        "data"
      ]
    }
  }
}