{
  "type": "Feature",
  "stac_version": "1.0.0",
  "id": "FM-5564-0014",
  "collection": "ncap-aerial",
  "geometry": {
    "type": "Polygon",
    "coordinates": [
      [
        [
          8.185389,
          40.977936
        ],
        [
          8.207332,
          41.01521
        ],
        [
          8.267072,
          40.995179
        ],
        [
          8.245129,
          40.957893
        ],
        [
          8.185389,
          40.977936
        ]
      ]
    ]
  },
  "bbox": [
    8.185389,
    40.957893,
    8.267072,
    41.01521
  ],
  "properties": {
    "datetime": "1939-01-01T00:00:00Z",
    "naph:tier": "Baseline",
    "naph:sortie": "FM/5564",
    "naph:perspective": "vertical",
    "naph:camera": "V",
    "naph:identifier": "https://w3id.org/naph/photo/FM-5564-0014",
    "naph:source": "https://airphotofinder.ncap.org/image/724946",
    "title": "FM/5564 frame 0014",
    "license": "other"
  },
  "links": [
    {
      "rel": "root",
      "href": "../../catalog.json",
      "type": "application/json"
    },
    {
      "rel": "parent",
      "href": "../../catalog.json",
      "type": "application/json"
    },
    {
      "rel": "self",
      "href": "./FM-5564-0014.json",
      "type": "application/geo+json"
    },
    {
      "rel": "collection",
      "href": "../../catalog.json",
      "type": "application/json"
    }
  ],
  "assets": {
    "catalogue": {
      "href": "https://airphotofinder.ncap.org/image/724946",
      "title": "Air Photo Finder catalogue record",
      "type": "text/html",
      "roles": [
        "overview",
        "metadata"
      ]
    },
    "image": {
      "href": "https://airphotofinder.ncap.org/image/724946",
      "title": "Digital surrogate (NCAP access copy)",
      "type": "image/tiff",
      "roles": [
        "data"
      ]
    }
  }
}